README.rst
setup.py
mznb/__init__.py
mznb/mznb.py
mznb_pdenno.egg-info/PKG-INFO
mznb_pdenno.egg-info/SOURCES.txt
mznb_pdenno.egg-info/dependency_links.txt
mznb_pdenno.egg-info/top_level.txt