Metadata-Version: 1.2
Name: mznb-pdenno
Version: 0.2.0
Summary: Magic to communicate between Jupyter notebooks and MiniZinc nb-agent
Home-page: https://github.com/pdenno/mznb/
Author: Peter Denno
Author-email: podenno@gmail.com
Maintainer: Peter Denno
Maintainer-email: podenno@gmail.com
License: BSD
Project-URL: Documentation, https://github.com/pdenno/mznb/
Project-URL: Code, https://github.com/pdenno/mznb/
Project-URL: Issue tracker, https://github.com/pdenno/mznb/issues
Platform: UNKNOWN
Classifier: Development Status :: 5 - Production/Stable
Classifier: Intended Audience :: Developers
Classifier: License :: OSI Approved :: BSD License
Classifier: Operating System :: OS Independent
Classifier: Programming Language :: Python
Classifier: Programming Language :: Python :: 2
Classifier: Programming Language :: Python :: 2.7
Classifier: Programming Language :: Python :: 3
Classifier: Programming Language :: Python :: 3.4
Classifier: Programming Language :: Python :: 3.5
Classifier: Programming Language :: Python :: 3.6
Classifier: Programming Language :: Python :: 3.7
Requires-Python: >=2.7, !=3.0.*, !=3.1.*, !=3.2.*, !=3.3.*
